.editorconfig
.gitignore
.gitlab-ci.yml
README.rst
publish.settings.sh
publish.sh
pyproject.toml
tsconfig.json
.idea/modules.xml
.idea/peek-core-email.iml
.idea/inspectionProfiles/Project_Default.xml
.idea/inspectionProfiles/profiles_settings.xml
peek_core_email/PlatformDependencyTest.py
peek_core_email/TempUnitTest.py
peek_core_email/__init__.py
peek_core_email/plugin_package.json
peek_core_email.egg-info/PKG-INFO
peek_core_email.egg-info/SOURCES.txt
peek_core_email.egg-info/dependency_links.txt
peek_core_email.egg-info/requires.txt
peek_core_email.egg-info/top_level.txt
peek_core_email/_private/PluginNames.py
peek_core_email/_private/__init__.py
peek_core_email/_private/alembic.ini
peek_core_email/_private/admin-app/PluginNames.ts
peek_core_email/_private/admin-app/core-email.module.ts
peek_core_email/_private/admin-app/components/core-email-page/core-email-admin.component.html
peek_core_email/_private/admin-app/components/core-email-page/core-email-admin.component.scss
peek_core_email/_private/admin-app/components/core-email-page/core-email-admin.component.ts
peek_core_email/_private/admin-app/components/setting-list/admin-setting-list.component.html
peek_core_email/_private/admin-app/components/setting-list/admin-setting-list.component.scss
peek_core_email/_private/admin-app/components/setting-list/admin-setting-list.component.ts
peek_core_email/_private/alembic/__init__.py
peek_core_email/_private/alembic/env.py
peek_core_email/_private/alembic/script.py.mako
peek_core_email/_private/alembic/versions/616e295c146d_initial.py
peek_core_email/_private/alembic/versions/__init__.py
peek_core_email/_private/server/EmailApi.py
peek_core_email/_private/server/PluginLogicEntryHook.py
peek_core_email/_private/server/__init__.py
peek_core_email/_private/server/admin_backend/PeekAdmSettingHandler.py
peek_core_email/_private/server/admin_backend/__init__.py
peek_core_email/_private/storage/DeclarativeBase.py
peek_core_email/_private/storage/Setting.py
peek_core_email/_private/storage/__init__.py
peek_core_email/admin-doc/index.rst
peek_core_email/admin-doc/admin_task/admin_tasks.rst
peek_core_email/admin-doc/admin_task/edit_email_settings.png
