Metadata-Version: 2.4
Name: peek-core-email
Version: 5.0.4
Summary: Peek Core Plugin Email - The active task plugin manages tasks that Peek may issue to users
Author-email: Synerty <contact@synerty.com>
Project-URL: Homepage, https://github.com/Synerty/peek-core-email
Keywords: Peek,Python,Platform,synerty
Requires-Dist: peek-plugin-base==5.0.4
